GavinReportPro/__init__.py
GavinReportPro/common.py
GavinReportPro/core/__init__.py
GavinReportPro/core/dataDriver.py
GavinReportPro/core/parameterized.py
GavinReportPro/core/reRun.py
GavinReportPro/core/resultPush.py
GavinReportPro/core/sendEmail.py
GavinReportPro/core/testResult.py
GavinReportPro/core/testRunner.py
GavinReportPro/templates/__init__.py
GavinReportPro/templates/dingtalk.md
GavinReportPro/templates/templates.html
GavinReportPro/templates/templates03.html
GavinReportPro/templates/templates2.html
GavinReportPro/templates/templates3.html
GavinReportPro-1.0.0.dist-info/LICENSE
GavinReportPro-1.0.0.dist-info/METADATA
GavinReportPro-1.0.0.dist-info/WHEEL
GavinReportPro-1.0.0.dist-info/top_level.txt
GavinReportPro-1.0.0.dist-info/RECORD
