Metadata-Version: 2.1
Name: GavinReportPro
Version: 1.0.0
Summary: Report for unittest
Author-email: GavinHaydy <bugpz2779@gmail.com>
Project-URL: Homepage, https://github.com/GavinHaydy/TheRuffianReportPro
Project-URL: download_page, https://codeload.github.com/GavinHaydy/TheRuffianReportPro/zip/refs/heads/master
Keywords: Gavin,GavinHaydy,ruffian,GavinReportPro
Classifier: Intended Audience :: Developers
Classifier: Operating System :: OS Independent
Classifier: Natural Language :: Chinese (Simplified)
Classifier: Programming Language :: Python :: 3
Classifier: Topic :: Software Development :: Testing
Classifier: Development Status :: 5 - Production/Stable
Classifier: License :: OSI Approved :: MIT License
Requires-Python: >=3.6
License-File: LICENSE
Requires-Dist: requests
Requires-Dist: PyYAML
Requires-Dist: Jinja2
